django_watch/__init__.py
django_watch/middleware.py
django_watch-0.5.3.dist-info/LICENSE
django_watch-0.5.3.dist-info/METADATA
django_watch-0.5.3.dist-info/WHEEL
django_watch-0.5.3.dist-info/top_level.txt
django_watch-0.5.3.dist-info/RECORD
