Metadata-Version: 2.1
Name: django-watch
Version: 0.5.3
Summary: Simple and useful django middleware for real-time logging.
Home-page: https://github.com/Sobolev5/django-watch/
Author: Sobolev Andrey
Author-email: email.asobolev@gmail.com
License: UNKNOWN
Platform: UNKNOWN
Classifier: Programming Language :: Python :: 3
Classifier: License :: OSI Approved :: MIT License
Classifier: Operating System :: OS Independent
Requires-Python: >=3.4
License-File: LICENSE
Requires-Dist: django (>=1.11)
